setup.py
maro/__init__.py
maro/scalike.py
maro.egg-info/PKG-INFO
maro.egg-info/SOURCES.txt
maro.egg-info/dependency_links.txt
maro.egg-info/namespace_packages.txt
maro.egg-info/top_level.txt