Metadata-Version: 1.0
Name: maro
Version: 0.0.1
Summary: `maro` is a package for exercises.
Home-page: https://bitbucket.org/imagawa_yakata/maro
Author: oyakata(imagawa_yakata)
Author-email: imagawa.yakata+maro at gmail.com
License: PSL
Keywords: oyakata,maro
Platform: UNKNOWN
Classifier: Development Status :: 1 - Planning
Classifier: Natural Language :: Japanese
Classifier: Programming Language :: Python
